lvc/__init__.py
lvc/dataset.py
lvc/inference_spect.py
lvc/inference_wav2vec.py
lvc/train.py
lvc/trainer.py
lvc/validation.py
lvc/weights.py
lvc/model/ResNetBlocks.py
lvc/model/ResNetSE34L.py
lvc/model/__init__.py
lvc/model/discriminator.py
lvc/model/ecapa_tdnn.py
lvc/model/generator.py
lvc/model/lvcnet.py
lvc/model/mpd.py
lvc/model/mrd.py
lvc/model/ssc.py
lvc/utils/__init__.py
lvc/utils/perturbations.py
lvc/utils/plotting.py
lvc/utils/stft.py
lvc/utils/stft_loss.py
lvc/utils/utils.py
lvc/utils/writer.py
lvc-1.0.3.dist-info/LICENSE
lvc-1.0.3.dist-info/METADATA
lvc-1.0.3.dist-info/WHEEL
lvc-1.0.3.dist-info/top_level.txt
lvc-1.0.3.dist-info/RECORD
