Metadata-Version: 2.1
Name: lvc
Version: 1.0.3
Summary: Unofficial pip package for zero-shot voice conversion
Home-page: https://github.com/fakerybakery/lvc
Author: mrfakename
License-File: LICENSE
Requires-Dist: librosa
Requires-Dist: soundfile
Requires-Dist: matplotlib
Requires-Dist: numpy
Requires-Dist: omegaconf
Requires-Dist: praat-parselmouth
Requires-Dist: scipy
Requires-Dist: tensorboard
Requires-Dist: torch
Requires-Dist: torchaudio
Requires-Dist: tqdm
Requires-Dist: transformers
Requires-Dist: cached-path
